zarrio/__init__.py
zarrio/api.py
zarrio/chunking.py
zarrio/cli.py
zarrio/config.py
zarrio/core.py
zarrio/exceptions.py
zarrio/missing.py
zarrio/models.py
zarrio/packing.py
zarrio/time.py
zarrio-0.1.1.dist-info/METADATA
zarrio-0.1.1.dist-info/WHEEL
zarrio-0.1.1.dist-info/entry_points.txt
zarrio-0.1.1.dist-info/top_level.txt
zarrio-0.1.1.dist-info/RECORD
