Metadata-Version: 2.4
Name: zarrio
Version: 0.1.1
Summary: A modern library for converting scientific data to Zarr format
Author-email: Oceanum Developers <developers@oceanum.science>
Maintainer-email: Oceanum Developers <developers@oceanum.science>
Project-URL: homepage, https://github.com/oceanum/zarrio
Project-URL: documentation, https://oceanum.github.io/zarrio
Project-URL: repository, https://github.com/oceanum/zarrio
Project-URL: issues, https://github.com/oceanum/zarrio/issues
Classifier: Development Status :: 3 - Alpha
Classifier: Intended Audience :: Developers
Classifier: Intended Audience :: Science/Research
Classifier: License :: OSI Approved :: MIT License
Classifier: Natural Language :: English
Classifier: Programming Language :: Python :: 3
Classifier: Programming Language :: Python :: 3.8
Classifier: Programming Language :: Python :: 3.9
Classifier: Programming Language :: Python :: 3.10
Classifier: Programming Language :: Python :: 3.11
Classifier: Programming Language :: Python :: 3.12
Classifier: Topic :: Scientific/Engineering
Classifier: Topic :: Software Development :: Libraries :: Python Modules
Requires-Dist: xarray>=0.18.0
Requires-Dist: zarr>=2.10.0
Requires-Dist: numpy>=1.20.0
Requires-Dist: pandas>=1.3.0
Requires-Dist: click>=8.0.0
Requires-Dist: pyyaml>=5.4.0
Requires-Dist: pyyaml>=5.4.0
Requires-Dist: dask
Requires-Dist: pydantic>2
Provides-Extra: oceanum
Requires-Dist: oceanum; extra == "oceanum"
Provides-Extra: dev
Requires-Dist: pytest>=6.2.0; extra == "dev"
Requires-Dist: pytest-cov>=2.12.0; extra == "dev"
Requires-Dist: black>=21.0.0; extra == "dev"
Requires-Dist: flake8>=3.9.0; extra == "dev"
Requires-Dist: mypy>=0.910; extra == "dev"
Requires-Dist: pre-commit>=2.13.0; extra == "dev"
Requires-Dist: tbump; extra == "dev"
Provides-Extra: docs
Requires-Dist: sphinx>=4.0.0; extra == "docs"
Requires-Dist: pydata-sphinx-theme; extra == "docs"
